{"_type":"export","__export_format":4,"__export_date":"2020-11-18T10:59:19.925Z","__export_source":"insomnia.desktop.app:v2020.4.2","resources":[{"_id":"req_981716da89fa49ff887488f41ab975b1","parentId":"wrk_90e5c6580f1346208bf23984753a1a1c","modified":1605691920561,"created":1605643173338,"url":"https://addons.huddu.io/application/8LhakwGkL8n2pRRSSNBuHx/","name":"Application","description":"","method":"GET","body":{},"parameters":[],"headers":[{"name":"Authorization","value":"Token 4cc5a09aad917578ca29fd3ee6481872085cbf55","description":"","id":"pair_8d5286d30c8c4cd6a50d5656991d67a5","disabled":false}],"authentication":{},"metaSortKey":-1605643150125,"isPrivate":false,"settingStoreCookies":true,"settingSendCookies":true,"settingDisableRenderRequestBody":false,"settingEncodeUrl":true,"settingRebuildPath":true,"settingFollowRedirects":"global","_type":"request"},{"_id":"wrk_90e5c6580f1346208bf23984753a1a1c","parentId":null,"modified":1604659312056,"created":1604659312056,"name":"Insomnia","description":"","scope":null,"_type":"workspace"},{"_id":"req_f946e80a30cd4ff5a187d0a64a69f1cc","parentId":"fld_f731ee96eb324e91a9d215106a641d2b","modified":1605692016791,"created":1605691957399,"url":"https://addons.huddu.io/application/8LhakwGkL8n2pRRSSNBuHx/current_status/","name":"Current Status","description":"","method":"GET","body":{},"parameters":[],"headers":[{"name":"Authorization","value":"Token 4cc5a09aad917578ca29fd3ee6481872085cbf55","description":"","id":"pair_8d5286d30c8c4cd6a50d5656991d67a5","disabled":false}],"authentication":{},"metaSortKey":-1605643173338,"isPrivate":false,"settingStoreCookies":true,"settingSendCookies":true,"settingDisableRenderRequestBody":false,"settingEncodeUrl":true,"settingRebuildPath":true,"settingFollowRedirects":"global","_type":"request"},{"_id":"fld_f731ee96eb324e91a9d215106a641d2b","parentId":"wrk_90e5c6580f1346208bf23984753a1a1c","modified":1605691998664,"created":1605643150075,"name":"Stats","description":"","environment":{},"environmentPropertyOrder":null,"metaSortKey":-1605643150075,"_type":"request_group"},{"_id":"req_02f7dced4f5c47a8a42b6f45428ac4d7","parentId":"fld_f731ee96eb324e91a9d215106a641d2b","modified":1605692025291,"created":1605692020872,"url":"https://addons.huddu.io/application/8LhakwGkL8n2pRRSSNBuHx/graphs/","name":"Graphs","description":"","method":"GET","body":{},"parameters":[],"headers":[{"name":"Authorization","value":"Token 4cc5a09aad917578ca29fd3ee6481872085cbf55","description":"","id":"pair_8d5286d30c8c4cd6a50d5656991d67a5","disabled":false}],"authentication":{},"metaSortKey":-1605643161731.5,"isPrivate":false,"settingStoreCookies":true,"settingSendCookies":true,"settingDisableRenderRequestBody":false,"settingEncodeUrl":true,"settingRebuildPath":true,"settingFollowRedirects":"global","_type":"request"},{"_id":"req_a64f9c249f0b4f9f860d329d231a1ed8","parentId":"fld_f9770e53f79d4d2bbcb4d3474e5ebbbc","modified":1605692125556,"created":1605692047658,"url":"https://addons.huddu.io/application/8LhakwGkL8n2pRRSSNBuHx/build/","name":"Build","description":"","method":"POST","body":{},"parameters":[],"headers":[{"name":"Authorization","value":"Token 4cc5a09aad917578ca29fd3ee6481872085cbf55","description":"","id":"pair_8d5286d30c8c4cd6a50d5656991d67a5","disabled":false}],"authentication":{},"metaSortKey":-1605643173338,"isPrivate":false,"settingStoreCookies":true,"settingSendCookies":true,"settingDisableRenderRequestBody":false,"settingEncodeUrl":true,"settingRebuildPath":true,"settingFollowRedirects":"global","_type":"request"},{"_id":"fld_f9770e53f79d4d2bbcb4d3474e5ebbbc","parentId":"wrk_90e5c6580f1346208bf23984753a1a1c","modified":1605692102334,"created":1605692047655,"name":"Deployment","description":"","environment":{},"environmentPropertyOrder":null,"metaSortKey":-1605643150025,"_type":"request_group"},{"_id":"req_ed9079b53d8545009bdcdbe81ab475d8","parentId":"fld_f9770e53f79d4d2bbcb4d3474e5ebbbc","modified":1605692224212,"created":1605692047661,"url":"https://addons.huddu.io/application/8LhakwGkL8n2pRRSSNBuHx/output/","name":"Output","description":"","method":"GET","body":{},"parameters":[],"headers":[{"name":"Authorization","value":"Token 4cc5a09aad917578ca29fd3ee6481872085cbf55","description":"","id":"pair_8d5286d30c8c4cd6a50d5656991d67a5","disabled":false}],"authentication":{},"metaSortKey":-1605643161731.5,"isPrivate":false,"settingStoreCookies":true,"settingSendCookies":true,"settingDisableRenderRequestBody":false,"settingEncodeUrl":true,"settingRebuildPath":true,"settingFollowRedirects":"global","_type":"request"},{"_id":"req_a2d25b771ae847d987e91ec1d6fb2ca6","parentId":"fld_f9770e53f79d4d2bbcb4d3474e5ebbbc","modified":1605692530746,"created":1605692247662,"url":"https://addons.huddu.io/application/8LhakwGkL8n2pRRSSNBuHx/deploy/github_repository/","name":"Github Repositiory","description":"","method":"GET","body":{},"parameters":[],"headers":[{"name":"Authorization","value":"Token 4cc5a09aad917578ca29fd3ee6481872085cbf55","description":"","id":"pair_8d5286d30c8c4cd6a50d5656991d67a5","disabled":false}],"authentication":{},"metaSortKey":-1605643155928.25,"isPrivate":false,"settingStoreCookies":true,"settingSendCookies":true,"settingDisableRenderRequestBody":false,"settingEncodeUrl":true,"settingRebuildPath":true,"settingFollowRedirects":"global","_type":"request"},{"_id":"req_a4705c22339f47479d47baff1bb5e732","parentId":"fld_4436c789c1b8457bb04a4403a88550cc","modified":1605692521183,"created":1605692492466,"url":"https://addons.huddu.io/application/8LhakwGkL8n2pRRSSNBuHx/language_packages/","name":"Language Packages","description":"","method":"GET","body":{},"parameters":[],"headers":[{"name":"Authorization","value":"Token 4cc5a09aad917578ca29fd3ee6481872085cbf55","description":"","id":"pair_8d5286d30c8c4cd6a50d5656991d67a5","disabled":false}],"authentication":{},"metaSortKey":-1605643173338,"isPrivate":false,"settingStoreCookies":true,"settingSendCookies":true,"settingDisableRenderRequestBody":false,"settingEncodeUrl":true,"settingRebuildPath":true,"settingFollowRedirects":"global","_type":"request"},{"_id":"fld_4436c789c1b8457bb04a4403a88550cc","parentId":"wrk_90e5c6580f1346208bf23984753a1a1c","modified":1605692492456,"created":1605692492456,"name":"Resources","description":"","environment":{},"environmentPropertyOrder":null,"metaSortKey":-1605643149975,"_type":"request_group"},{"_id":"req_cc051c33bb3d49ca98c2d8737f05b4ce","parentId":"fld_4436c789c1b8457bb04a4403a88550cc","modified":1605692617207,"created":1605692492473,"url":"https://addons.huddu.io/application/8LhakwGkL8n2pRRSSNBuHx/language_packages/","name":"Language Packages","description":"","method":"POST","body":{"mimeType":"multipart/form-data","params":[{"name":"language_package","value":"language_package_git_link","description":"","id":"pair_0defbbef34584574871a462bf923fa9c"}]},"parameters":[],"headers":[{"name":"Authorization","value":"Token 4cc5a09aad917578ca29fd3ee6481872085cbf55","description":"","id":"pair_8d5286d30c8c4cd6a50d5656991d67a5","disabled":false},{"name":"Content-Type","value":"multipart/form-data","id":"pair_891d3e7d048a4b6cbdf7ce85db652e58"}],"authentication":{},"metaSortKey":-1605643161731.5,"isPrivate":false,"settingStoreCookies":true,"settingSendCookies":true,"settingDisableRenderRequestBody":false,"settingEncodeUrl":true,"settingRebuildPath":true,"settingFollowRedirects":"global","_type":"request"},{"_id":"req_345dd2ec60764c35ab1bf6660f229175","parentId":"fld_4436c789c1b8457bb04a4403a88550cc","modified":1605692632135,"created":1605692492475,"url":"https://addons.huddu.io/application/8LhakwGkL8n2pRRSSNBuHx/launchers/","name":"Launchers","description":"","method":"GET","body":{},"parameters":[],"headers":[{"name":"Authorization","value":"Token 4cc5a09aad917578ca29fd3ee6481872085cbf55","description":"","id":"pair_8d5286d30c8c4cd6a50d5656991d67a5","disabled":false}],"authentication":{},"metaSortKey":-1605643155928.25,"isPrivate":false,"settingStoreCookies":true,"settingSendCookies":true,"settingDisableRenderRequestBody":false,"settingEncodeUrl":true,"settingRebuildPath":true,"settingFollowRedirects":"global","_type":"request"},{"_id":"req_9dfddbdc9cc8447ea1fa0853b5923645","parentId":"fld_4436c789c1b8457bb04a4403a88550cc","modified":1605692619796,"created":1605692579763,"url":"https://addons.huddu.io/application/8LhakwGkL8n2pRRSSNBuHx/language_packages/","name":"Language Packages","description":"","method":"DELETE","body":{"mimeType":"multipart/form-data","params":[{"name":"language_package","value":"language_package_git_link","description":"","id":"pair_0defbbef34584574871a462bf923fa9c"}]},"parameters":[],"headers":[{"name":"Authorization","value":"Token 4cc5a09aad917578ca29fd3ee6481872085cbf55","description":"","id":"pair_8d5286d30c8c4cd6a50d5656991d67a5","disabled":false},{"name":"Content-Type","value":"multipart/form-data","id":"pair_891d3e7d048a4b6cbdf7ce85db652e58"}],"authentication":{},"metaSortKey":-1605643158829.875,"isPrivate":false,"settingStoreCookies":true,"settingSendCookies":true,"settingDisableRenderRequestBody":false,"settingEncodeUrl":true,"settingRebuildPath":true,"settingFollowRedirects":"global","_type":"request"},{"_id":"req_73b98347071b41e99bc500fd0cb826bb","parentId":"fld_4436c789c1b8457bb04a4403a88550cc","modified":1605692653814,"created":1605692635545,"url":"https://addons.huddu.io/application/8LhakwGkL8n2pRRSSNBuHx/launchers/","name":"Launchers","description":"","method":"POST","body":{"mimeType":"multipart/form-data","params":[{"name":"launcher","value":"launcher","description":"","id":"pair_62359faacdc74837b1a45ade34d189af"}]},"parameters":[],"headers":[{"name":"Authorization","value":"Token 4cc5a09aad917578ca29fd3ee6481872085cbf55","description":"","id":"pair_8d5286d30c8c4cd6a50d5656991d67a5","disabled":false},{"name":"Content-Type","value":"multipart/form-data","id":"pair_5f9ac2b98a6649639fb1fa366c49ca76"}],"authentication":{},"metaSortKey":-1605643153026.625,"isPrivate":false,"settingStoreCookies":true,"settingSendCookies":true,"settingDisableRenderRequestBody":false,"settingEncodeUrl":true,"settingRebuildPath":true,"settingFollowRedirects":"global","_type":"request"},{"_id":"req_e3558402fc074f47860e1cec7cf45499","parentId":"fld_4436c789c1b8457bb04a4403a88550cc","modified":1605692660505,"created":1605692658044,"url":"https://addons.huddu.io/application/8LhakwGkL8n2pRRSSNBuHx/launchers/","name":"Launchers","description":"","method":"DELETE","body":{"mimeType":"multipart/form-data","params":[{"name":"launcher","value":"launcher","description":"","id":"pair_62359faacdc74837b1a45ade34d189af"}]},"parameters":[],"headers":[{"name":"Authorization","value":"Token 4cc5a09aad917578ca29fd3ee6481872085cbf55","description":"","id":"pair_8d5286d30c8c4cd6a50d5656991d67a5","disabled":false},{"name":"Content-Type","value":"multipart/form-data","id":"pair_5f9ac2b98a6649639fb1fa366c49ca76"}],"authentication":{},"metaSortKey":-1605643151575.8125,"isPrivate":false,"settingStoreCookies":true,"settingSendCookies":true,"settingDisableRenderRequestBody":false,"settingEncodeUrl":true,"settingRebuildPath":true,"settingFollowRedirects":"global","_type":"request"},{"_id":"req_827f3caf369e4c99a1d3d7fcde5e5247","parentId":"fld_6a1774bce59f4ea799fa399d57952481","modified":1605696733981,"created":1605696712611,"url":"https://addons.huddu.io/application/8LhakwGkL8n2pRRSSNBuHx/files/tree/","name":"Filetree","description":"","method":"GET","body":{},"parameters":[],"headers":[{"name":"Authorization","value":"Token 4cc5a09aad917578ca29fd3ee6481872085cbf55","description":"","id":"pair_8d5286d30c8c4cd6a50d5656991d67a5","disabled":false}],"authentication":{},"metaSortKey":-1605643173338,"isPrivate":false,"settingStoreCookies":true,"settingSendCookies":true,"settingDisableRenderRequestBody":false,"settingEncodeUrl":true,"settingRebuildPath":true,"settingFollowRedirects":"global","_type":"request"},{"_id":"fld_6a1774bce59f4ea799fa399d57952481","parentId":"wrk_90e5c6580f1346208bf23984753a1a1c","modified":1605696712603,"created":1605696712603,"name":"Files","description":"","environment":{},"environmentPropertyOrder":null,"metaSortKey":-1605643150000,"_type":"request_group"},{"_id":"req_ecc8e88699ff4522bfad44cba8c16224","parentId":"fld_6a1774bce59f4ea799fa399d57952481","modified":1605697010191,"created":1605696712620,"url":"https://addons.huddu.io/application/8LhakwGkL8n2pRRSSNBuHx/file?file={filename}","name":"File","description":"","method":"GET","body":{"mimeType":"application/x-www-form-urlencoded","params":[]},"parameters":[],"headers":[{"name":"Authorization","value":"Token 4cc5a09aad917578ca29fd3ee6481872085cbf55","description":"","id":"pair_8d5286d30c8c4cd6a50d5656991d67a5","disabled":false},{"name":"Content-Type","value":"application/x-www-form-urlencoded","id":"pair_ec2d503ecf024fd0830b9169323cf29d"}],"authentication":{},"metaSortKey":-1605643161731.5,"isPrivate":false,"settingStoreCookies":true,"settingSendCookies":true,"settingDisableRenderRequestBody":false,"settingEncodeUrl":true,"settingRebuildPath":true,"settingFollowRedirects":"global","_type":"request"},{"_id":"req_75094aae701040dd9e206856fbb40053","parentId":"fld_6a1774bce59f4ea799fa399d57952481","modified":1605697061742,"created":1605696712623,"url":"https://addons.huddu.io/application/8LhakwGkL8n2pRRSSNBuHx/file/","name":"File","description":"","method":"POST","body":{"mimeType":"application/x-www-form-urlencoded","params":[{"name":"file","value":"filename","description":"","id":"pair_94cc76fa2ec240359a4104bd3a9be5ea"},{"name":"content","value":"content","description":"","id":"pair_5b9b6f77135a4c5b908a62c89c3a834b"}]},"parameters":[],"headers":[{"name":"Authorization","value":"Token 4cc5a09aad917578ca29fd3ee6481872085cbf55","description":"","id":"pair_8d5286d30c8c4cd6a50d5656991d67a5","disabled":false},{"name":"Content-Type","value":"application/x-www-form-urlencoded","id":"pair_b88e3c31b4c7470db7c13c54eb8fa69a"}],"authentication":{},"metaSortKey":-1605643155928.25,"isPrivate":false,"settingStoreCookies":true,"settingSendCookies":true,"settingDisableRenderRequestBody":false,"settingEncodeUrl":true,"settingRebuildPath":true,"settingFollowRedirects":"global","_type":"request"},{"_id":"req_b700cf71acdd49d5a38365f11a1561a2","parentId":"fld_6a1774bce59f4ea799fa399d57952481","modified":1605697074736,"created":1605697070466,"url":"https://addons.huddu.io/application/8LhakwGkL8n2pRRSSNBuHx/file/","name":"File","description":"","method":"DELETE","body":{"mimeType":"application/x-www-form-urlencoded","params":[{"name":"file","value":"filename","description":"","id":"pair_94cc76fa2ec240359a4104bd3a9be5ea"}]},"parameters":[],"headers":[{"name":"Authorization","value":"Token 4cc5a09aad917578ca29fd3ee6481872085cbf55","description":"","id":"pair_8d5286d30c8c4cd6a50d5656991d67a5","disabled":false},{"name":"Content-Type","value":"application/x-www-form-urlencoded","id":"pair_b88e3c31b4c7470db7c13c54eb8fa69a"}],"authentication":{},"metaSortKey":-1605643154477.4375,"isPrivate":false,"settingStoreCookies":true,"settingSendCookies":true,"settingDisableRenderRequestBody":false,"settingEncodeUrl":true,"settingRebuildPath":true,"settingFollowRedirects":"global","_type":"request"},{"_id":"req_fe261b90f3d44771be0a34a8960074e0","parentId":"fld_6a1774bce59f4ea799fa399d57952481","modified":1605697119350,"created":1605697108435,"url":"https://addons.huddu.io/application/8LhakwGkL8n2pRRSSNBuHx/application_logs/","name":"Application Logs","description":"","method":"GET","body":{"mimeType":"application/x-www-form-urlencoded","params":[{"name":"file","value":"filename","description":"","id":"pair_94cc76fa2ec240359a4104bd3a9be5ea"}]},"parameters":[],"headers":[{"name":"Authorization","value":"Token 4cc5a09aad917578ca29fd3ee6481872085cbf55","description":"","id":"pair_8d5286d30c8c4cd6a50d5656991d67a5","disabled":false},{"name":"Content-Type","value":"application/x-www-form-urlencoded","id":"pair_b88e3c31b4c7470db7c13c54eb8fa69a"}],"authentication":{},"metaSortKey":-1605643153752.0312,"isPrivate":false,"settingStoreCookies":true,"settingSendCookies":true,"settingDisableRenderRequestBody":false,"settingEncodeUrl":true,"settingRebuildPath":true,"settingFollowRedirects":"global","_type":"request"},{"_id":"env_1a776df21b96ddfbd26c2ae3bce3cdea0c4bfeb9","parentId":"wrk_90e5c6580f1346208bf23984753a1a1c","modified":1605643008584,"created":1604659312097,"name":"Base Environment","data":{},"dataPropertyOrder":{},"color":null,"isPrivate":false,"metaSortKey":1604659312097,"_type":"environment"},{"_id":"jar_1a776df21b96ddfbd26c2ae3bce3cdea0c4bfeb9","parentId":"wrk_90e5c6580f1346208bf23984753a1a1c","modified":1605627751360,"created":1604659312099,"name":"Default Jar","cookies":[{"key":"__cfduid","value":"dae5aae198f2e1487972daee6375d2fad1605627751","expires":"2020-12-17T15:42:31.000Z","domain":"huddu.io","path":"/","secure":true,"httpOnly":true,"extensions":["SameSite=Lax"],"hostOnly":false,"creation":"2020-11-17T15:42:31.355Z","lastAccessed":"2020-11-17T15:42:31.355Z","id":"9245951914256709"}],"_type":"cookie_jar"},{"_id":"spc_c93d011599d548c7a911a55a54c0d043","parentId":"wrk_90e5c6580f1346208bf23984753a1a1c","modified":1604659312057,"created":1604659312057,"fileName":"Insomnia","contents":"","contentType":"yaml","_type":"api_spec"},{"_id":"env_c6d0f8dc66ad43bba33eeb1a5a3bd1d2","parentId":"env_1a776df21b96ddfbd26c2ae3bce3cdea0c4bfeb9","modified":1605643021637,"created":1605643013112,"name":"Production","data":{},"dataPropertyOrder":null,"color":null,"isPrivate":false,"metaSortKey":1605643013112,"_type":"environment"}]}